{
  "1": {
    "id": "1",
    "itemType": 1,
    "icon": "item_1",
    "itemName": "401001",
    "itemDesc": "402001",
    "grade": 5,
    "gain_item": null,
    "skill_learn": ""
  },
  "2": {
    "id": "2",
    "itemType": 1,
    "icon": "item_2",
    "itemName": "401002",
    "itemDesc": "402002",
    "grade": 4,
    "gain_item": null,
    "skill_learn": ""
  },
  "3": {
    "id": "3",
    "itemType": 1,
    "icon": "item_3",
    "itemName": "401003",
    "itemDesc": "402003",
    "grade": 4,
    "gain_item": null,
    "skill_learn": ""
  },
  "4": {
    "id": "4",
    "itemType": 1,
    "icon": "item_4",
    "itemName": "401004",
    "itemDesc": "402004",
    "grade": 4,
    "gain_item": null,
    "skill_learn": ""
  },
  "5": {
    "id": "5",
    "itemType": 1,
    "icon": "item_5",
    "itemName": "401005",
    "itemDesc": "402005",
    "grade": 5,
    "gain_item": null,
    "skill_learn": ""
  },
  "6": {
    "id": "6",
    "itemType": 1,
    "icon": "item_6",
    "itemName": "401006",
    "itemDesc": "402006",
    "grade": 5,
    "gain_item": null,
    "skill_learn": ""
  },
  "7": {
    "id": "7",
    "itemType": 1,
    "icon": "item_7",
    "itemName": "401007",
    "itemDesc": "402007",
    "grade": 4,
    "gain_item": null,
    "skill_learn": ""
  },
  "8": {
    "id": "8",
    "itemType": 1,
    "icon": "item_8",
    "itemName": "401008",
    "itemDesc": "402008",
    "grade": 3,
    "gain_item": null,
    "skill_learn": ""
  },
  "9": {
    "id": "9",
    "itemType": 1,
    "icon": "item_9",
    "itemName": "401009",
    "itemDesc": "402009",
    "grade": 3,
    "gain_item": null,
    "skill_learn": ""
  },
  "10": {
    "id": "10",
    "itemType": 1,
    "icon": "item_10",
    "itemName": "401010",
    "itemDesc": "",
    "grade": 3,
    "gain_item": null,
    "skill_learn": ""
  },
  "11": {
    "id": "11",
    "itemType": 1,
    "icon": "item_11",
    "itemName": "401011",
    "itemDesc": "",
    "grade": 3,
    "gain_item": null,
    "skill_learn": ""
  },
  "12": {
    "id": "12",
    "itemType": 2,
    "icon": "icon_8001",
    "itemName": "401012",
    "itemDesc": "402012",
    "grade": 3,
    "gain_item": [
      1,
      "8001",
      30
    ],
    "skill_learn": ""
  },
  "13": {
    "id": "13",
    "itemType": 2,
    "icon": "icon_8001",
    "itemName": "401013",
    "itemDesc": "402013",
    "grade": 4,
    "gain_item": [
      1,
      "8001",
      100
    ],
    "skill_learn": ""
  },
  "14": {
    "id": "14",
    "itemType": 2,
    "icon": "icon_8002",
    "itemName": "401014",
    "itemDesc": "402014",
    "grade": 3,
    "gain_item": [
      1,
      "8002",
      30
    ],
    "skill_learn": ""
  },
  "15": {
    "id": "15",
    "itemType": 2,
    "icon": "icon_8002",
    "itemName": "401015",
    "itemDesc": "402015",
    "grade": 4,
    "gain_item": [
      1,
      "8002",
      100
    ],
    "skill_learn": ""
  },
  "16": {
    "id": "16",
    "itemType": 2,
    "icon": "icon_8003",
    "itemName": "401016",
    "itemDesc": "402016",
    "grade": 3,
    "gain_item": [
      1,
      "8003",
      30
    ],
    "skill_learn": ""
  },
  "17": {
    "id": "17",
    "itemType": 2,
    "icon": "icon_8003",
    "itemName": "401017",
    "itemDesc": "402017",
    "grade": 4,
    "gain_item": [
      1,
      "8003",
      100
    ],
    "skill_learn": ""
  },
  "18": {
    "id": "18",
    "itemType": 1,
    "icon": "item_18",
    "itemName": "401018",
    "itemDesc": "402018",
    "grade": 4,
    "gain_item": null,
    "skill_learn": ""
  },
  "19": {
    "id": "19",
    "itemType": 1,
    "icon": "item_18",
    "itemName": "401025",
    "itemDesc": "402019",
    "grade": 4,
    "gain_item": null,
    "skill_learn": ""
  },
  "20": {
    "id": "20",
    "itemType": 1,
    "icon": "",
    "itemName": "",
    "itemDesc": "",
    "grade": null,
    "gain_item": null,
    "skill_learn": ""
  },
  "5001": {
    "id": "5001",
    "itemType": 3,
    "icon": "",
    "itemName": "108001",
    "itemDesc": "1080011",
    "grade": 1,
    "gain_item": null,
    "skill_learn": "50001"
  },
  "8001": {
    "id": "8001",
    "itemType": 0,
    "icon": "icon_8001",
    "itemName": "401019",
    "itemDesc": "",
    "grade": 1,
    "gain_item": null,
    "skill_learn": ""
  },
  "8002": {
    "id": "8002",
    "itemType": 0,
    "icon": "icon_8002",
    "itemName": "401020",
    "itemDesc": "",
    "grade": 1,
    "gain_item": null,
    "skill_learn": ""
  },
  "8003": {
    "id": "8003",
    "itemType": 0,
    "icon": "icon_8003",
    "itemName": "401021",
    "itemDesc": "",
    "grade": 1,
    "gain_item": null,
    "skill_learn": ""
  },
  "8004": {
    "id": "8004",
    "itemType": 0,
    "icon": "icon_8004",
    "itemName": "401022",
    "itemDesc": "",
    "grade": 1,
    "gain_item": null,
    "skill_learn": ""
  },
  "8005": {
    "id": "8005",
    "itemType": 0,
    "icon": "icon_8005",
    "itemName": "401023",
    "itemDesc": "",
    "grade": 4,
    "gain_item": null,
    "skill_learn": ""
  },
  "8006": {
    "id": "8006",
    "itemType": 0,
    "icon": "icon_8006",
    "itemName": "401024",
    "itemDesc": "",
    "grade": 1,
    "gain_item": null,
    "skill_learn": ""
  },
  "8007": {
    "id": "8007",
    "itemType": 0,
    "icon": "",
    "itemName": "",
    "itemDesc": "",
    "grade": 1,
    "gain_item": null,
    "skill_learn": ""
  }
}